cythoneuclideandistance/README.MD
cythoneuclideandistance/__init__.py
cythoneuclideandistance/requirements.txt
cythoneuclideandistance/thirdparty.json
cythoneuclideandistance-0.11.dist-info/LICENSE.rst
cythoneuclideandistance-0.11.dist-info/METADATA
cythoneuclideandistance-0.11.dist-info/WHEEL
cythoneuclideandistance-0.11.dist-info/top_level.txt
cythoneuclideandistance-0.11.dist-info/RECORD
