Metadata-Version: 2.1
Name: cythoneuclideandistance
Version: 0.11
Summary: Calculate Euclidean distances between two sets of coordinates (Cython and Numexpr)
Home-page: https://github.com/hansalemaos/cythoneuclideandistance
Author: Johannes Fischer
Author-email: aulasparticularesdealemaosp@gmail.com
License: MIT
Keywords: Calculate Euclidean
Classifier: Development Status :: 4 - Beta
Classifier: Programming Language :: Python :: 3 :: Only
Classifier: Programming Language :: Python :: 3.10
Classifier: Topic :: Software Development :: Libraries :: Python Modules
Classifier: Topic :: Utilities
License-File: LICENSE.rst
Requires-Dist: Cython
Requires-Dist: numexpr
Requires-Dist: numpy
